quick_menu/__about__.py
quick_menu/__init__.py
quick_menu/menu.py
quick_menu-0.6.0.dist-info/METADATA
quick_menu-0.6.0.dist-info/WHEEL
quick_menu-0.6.0.dist-info/licenses/LICENSE.txt
quick_menu-0.6.0.dist-info/RECORD
