Metadata-Version: 2.1
Name: quick-menu
Version: 0.6.0
Summary: A simple package to create text menus for use in console applications
Project-URL: Documentation, https://yqbear.github.io/quick-menu
Project-URL: Issues, https://github.com/yqbear/quick-menu/issues
Project-URL: Source, https://github.com/yqbear/quick-menu
Author-email: Stephan Poole <yqbear@gmail.com>
License-Expression: MIT
License-File: LICENSE.txt
Classifier: Development Status :: 4 - Beta
Classifier: Environment :: Console
Classifier: Programming Language :: Python
Classifier: Programming Language :: Python :: 3.7
Classifier: Programming Language :: Python :: 3.8
Classifier: Programming Language :: Python :: 3.9
Classifier: Programming Language :: Python :: 3.10
Classifier: Programming Language :: Python :: 3.11
Classifier: Programming Language :: Python :: Implementation :: CPython
Classifier: Programming Language :: Python :: Implementation :: PyPy
Requires-Python: >=3.7
Requires-Dist: typing-extensions
